weibo_api/__init__.py
weibo_api/client.py
weibo_api/config/__init__.py
weibo_api/config/urls.py
weibo_api/utils/__init__.py
weibo_api/utils/exception.py
weibo_api/utils/normal.py
weibo_api/utils/streaming.py
weibo_api/utils/utils.py
weibo_api/weibo/__init__.py
weibo_api/weibo/article.py
weibo_api/weibo/base.py
weibo_api/weibo/people.py
weibo_api/weibo/pic.py
weibo_api/weibo/status.py
weibo_api/weibo/video.py
weibo_api-0.0.4.dist-info/DESCRIPTION.rst
weibo_api-0.0.4.dist-info/LICENSE.txt
weibo_api-0.0.4.dist-info/METADATA
weibo_api-0.0.4.dist-info/RECORD
weibo_api-0.0.4.dist-info/WHEEL
weibo_api-0.0.4.dist-info/metadata.json
weibo_api-0.0.4.dist-info/top_level.txt
