Metadata-Version: 2.0
Name: weibo-api
Version: 0.0.4
Summary: 对微博m站API进行封装，提供简单易用的用户接口来免登陆获取微博数据
Home-page: https://github.com/hukaixuan/weibo-api
Author: hukaixuan
Author-email: hukx.michael@gmail.com
License: MIT
Keywords: weibo,network,http,JSON
Platform: UNKNOWN
Classifier: Development Status :: 3 - Alpha
Classifier: Environment :: Web Environment
Classifier: Intended Audience :: Developers
Classifier: License :: OSI Approved :: MIT License
Classifier: Operating System :: OS Independent
Classifier: Programming Language :: Python
Classifier: Programming Language :: Python :: 2.7
Classifier: Programming Language :: Python :: 3.5
Classifier: Programming Language :: Python :: 3.6
Classifier: Topic :: Internet :: WWW/HTTP
Classifier: Topic :: Software Development :: Libraries :: Python Modules
Requires-Dist: requests (>=2.10.0)
